{
  "products": ["产品A", "产品B", "产品C", "产品D"],
  "resources": ["资源1", "资源2", "资源3", "资源4"],
  "profits": {
    "产品A": 8,
    "产品B": 7,
    "产品C": 6,
    "产品D": 5
  },
  "limits": {
    "资源1": 80,
    "资源2": 72,
    "资源3": 68,
    "资源4": 60
  },
  "consumption": {
    "产品A": {
      "资源1": 4,
      "资源2": 2,
      "资源3": 3,
      "资源4": 1
    },
    "产品B": {
      "资源1": 3,
      "资源2": 4,
      "资源3": 2,
      "资源4": 2
    },
    "产品C": {
      "资源1": 2,
      "资源2": 3,
      "资源3": 4,
      "资源4": 3
    },
    "产品D": {
      "资源1": 1,
      "资源2": 2,
      "资源3": 3,
      "资源4": 4
    }
  }
}
